[
    {
        "query": "What is the title of Karl Marx's work that analyzes capitalism?",
        "level": "2",
        "subject": "Karl Marx",
        "answer": "Das Kapital",
        "type": "simple question"
    },
    {
        "query": "In what country was Karl Marx born?",
        "level": "2",
        "subject": "Karl Marx",
        "answer": "Prussia",
        "type": "simple question"
    },
    {
        "query": "What university did Karl Marx receive his doctorate in philosophy from?",
        "level": "2",
        "subject": "Karl Marx",
        "answer": "University of Jena",
        "type": "simple question"
    },
    {
        "query": "Who was Karl Marx's lifelong friend and collaborator?",
        "level": "2",
        "subject": "Karl Marx",
        "answer": "Friedrich Engels",
        "type": "simple question"
    },
    {
        "query": "In which cemetery is Karl Marx buried?",
        "level": "2",
        "subject": "Karl Marx",
        "answer": "Highgate Cemetery",
        "type": "simple question"
    },
    {
        "query": "What is the name of the pamphlet that Karl Marx is best known for?",
        "level": "2",
        "subject": "Karl Marx",
        "answer": "The Communist Manifesto",
        "type": "simple question"
    },
    {
        "query": "In what city did Karl Marx meet Friedrich Engels?",
        "level": "2",
        "subject": "Karl Marx",
        "answer": "Paris",
        "type": "simple question"
    },
    {
        "query": "What university did Karl Marx receive his doctorate in philosophy from?",
        "level": "2",
        "subject": "Karl Marx",
        "answer": "University of Jena",
        "type": "simple question"
    },
    {
        "query": "Who was Karl Marx's lifelong friend and collaborator?",
        "level": "2",
        "subject": "Karl Marx",
        "answer": "Friedrich Engels",
        "type": "simple question"
    },
    {
        "query": "Which organization did Marx help to found in 1864?",
        "level": "2",
        "subject": "Karl Marx",
        "answer": "International Workingmen's Association (First International)",
        "type": "simple question"
    },
    {
        "query": "What name did Marx's father take after converting from Judaism?",
        "level": "2",
        "subject": "Karl Marx",
        "answer": "Heinrich",
        "type": "simple question"
    },
    {
        "query": "Which university did Marx transfer to after the University of Bonn?",
        "level": "2",
        "subject": "Karl Marx",
        "answer": "University of Berlin",
        "type": "simple question"
    },
    {
        "query": "In which city was Karl Marx born?",
        "level": "2",
        "subject": "Karl Marx",
        "answer": "Trier",
        "type": "simple question"
    },
    {
        "query": "What was Karl Marx's professional background of his father?",
        "level": "2",
        "subject": "Karl Marx",
        "answer": "lawyer",
        "type": "simple question"
    },
    {
        "query": "Which university did Karl Marx matriculate in the faculty of law?",
        "level": "2",
        "subject": "Karl Marx",
        "answer": "University of Berlin",
        "type": "simple question"
    },
    {
        "query": "What was the title of Karl Marx's doctoral thesis?",
        "level": "2",
        "subject": "Karl Marx",
        "answer": "The Difference Between the Democritean and Epicurean Philosophy of Nature",
        "type": "simple question"
    },
    {
        "query": "What university awarded Karl Marx his Ph.D.?",
        "level": "2",
        "subject": "Karl Marx",
        "answer": "University of Jena",
        "type": "simple question"
    },
    {
        "query": "Which newspaper did Karl Marx write for that was shut down by Prussian government censorship?",
        "level": "2",
        "subject": "Karl Marx",
        "answer": "Rheinische Zeitung",
        "type": "simple question"
    },
    {
        "query": "In what year did Marx and Jenny von Westphalen get married?",
        "level": "2",
        "subject": "Karl Marx",
        "answer": "1843",
        "type": "simple question"
    },
    {
        "query": "What university did Karl Marx attend in 1836?",
        "level": "2",
        "subject": "Karl Marx",
        "answer": "University of Berlin",
        "type": "simple question"
    }
]