[
    {
        "query": "What film did Brooke Shields star in at the age of 12?",
        "level": "2",
        "subject": "Brooke Shields",
        "answer": "Pretty Baby",
        "type": "simple question"
    },
    {
        "query": "Which university did Brooke Shields attend?",
        "level": "2",
        "subject": "Brooke Shields",
        "answer": "Princeton University",
        "type": "simple question"
    },
    {
        "query": "Which sitcom earned Brooke Shields two Golden Globe nominations?",
        "level": "2",
        "subject": "Brooke Shields",
        "answer": "Suddenly Susan",
        "type": "simple question"
    },
    {
        "query": "For which film did Brooke Shields gain widespread notoriety at age 12?",
        "level": "2",
        "subject": "Brooke Shields",
        "answer": "Pretty Baby",
        "type": "simple question"
    },
    {
        "query": "In which film did Brooke Shields appear in nude scenes at the age of 11?",
        "level": "2",
        "subject": "Brooke Shields",
        "answer": "Pretty Baby",
        "type": "simple question"
    },
    {
        "query": "Which sitcom earned Brooke Shields two Golden Globe nominations?",
        "level": "2",
        "subject": "Brooke Shields",
        "answer": "Suddenly Susan",
        "type": "simple question"
    },
    {
        "query": "What film did Brooke Shields star in at age 12?",
        "level": "2",
        "subject": "Brooke Shields",
        "answer": "Pretty Baby",
        "type": "simple question"
    },
    {
        "query": "Which university did Brooke Shields attend?",
        "level": "2",
        "subject": "Brooke Shields",
        "answer": "Princeton University",
        "type": "simple question"
    },
    {
        "query": "Which television show did Brooke Shields join in its 19th season in 2017?",
        "level": "2",
        "subject": "Brooke Shields",
        "answer": "Law & Order: Special Victims Unit",
        "type": "simple question"
    },
    {
        "query": "What is the name of Brooke Shields' mother?",
        "level": "2",
        "subject": "Brooke Shields",
        "answer": "Teri Shields",
        "type": "simple question"
    }
]