[
    {
        "subject": "Brett Favre",
        "question": "Brenda Ann Spencer\u2019s justification for opening fire at a San Diego school on January 29th 1979 inspired which song by The Boomtown Rats?",
        "answers": [
            "I hate Mondays",
            "I Don't Like Mondays (Song)",
            "I dont like mondays",
            "I hate mondays",
            "I don't like mondays",
            "I Don\u2019t Like Mondays",
            "I Don't Like Mondays (song)",
            "I don't like Mondays",
            "I Don't Like Mondays"
        ]
    },
    {
        "subject": "Brett Favre",
        "question": "The International Bureau of Weights and Measures is based in which European country?",
        "answers": [
            "La Republique francaise",
            "Franciaorsz\u00e1g",
            "La Republique fran\u00e7aise",
            "Belle France",
            "FRANCE",
            "Republique fran\u00e7aise",
            "France",
            "Ranska",
            "Franciaorszag",
            "French Republic",
            "R\u00e9publique francaise",
            "R\u00e9publique fran\u00e7aise",
            "ISO 3166-1:FR",
            "Frankreich",
            "France (country)",
            "Etymology of France",
            "FrancE",
            "La R\u00e9publique fran\u00e7aise",
            "People of France",
            "Republic of France",
            "Fracne",
            "Le France",
            "The French Republic",
            "Republique francaise",
            "The Republic of France",
            "La R\u00e9publique francaise",
            "La France",
            "Rain in France",
            "Republic of france",
            "FRance",
            "Frakkland",
            "Climate of France",
            "Franse"
        ]
    },
    {
        "subject": "Brett Favre",
        "question": "In which sport did Duncan Goodhew excel?",
        "answers": [
            "Swam",
            "Swimming (disambiguation)",
            "To-suijutsu",
            "Swimming"
        ]
    },
    {
        "subject": "Brett Favre",
        "question": "Which college\u2019s chapel doubles as Oxford\u2019s cathedral?",
        "answers": [
            "Christ Church",
            "Christ Church (disambiguation)"
        ]
    },
    {
        "subject": "Brett Favre",
        "question": "Who wrote 'The Legend Of Sleepy Hollow'?",
        "answers": [
            "Kickerbocker's History",
            "Diedrich Knickerbocker",
            "Washington Irving",
            "Friar Antonio Agapido",
            "A History of New-York",
            "Sketch Book",
            "An American Gentleman",
            "A History of New York",
            "Irvingian",
            "Dietrich Knickerbocker",
            "Knickerbocker's History of New York",
            "W. Irving",
            "WASHINGTON IRVING",
            "George W. Irving",
            "Kickerbocker's History of New-York"
        ]
    },
    {
        "subject": "Brett Favre",
        "question": "What is the name of the Welsh television producer and writer who created 'Torchwood'?",
        "answers": [
            "Stephen Russell Davies",
            "Russel T. Davies",
            "Doctor Who: The Writer's Tale",
            "Russell T. Davis",
            "Russell T Davis",
            "The Writer's Tale",
            "Russell T. Davies",
            "Russell T. Davies, OBE",
            "RUSSELL T. DAVIES",
            "Russell T Davies"
        ]
    },
    {
        "subject": "Brett Favre",
        "question": "Who became head coach of Sunderland in March 2015?",
        "answers": [
            "Advocaat, Dick",
            "Dick Advocaat"
        ]
    },
    {
        "subject": "Brett Favre",
        "question": "Which London residential suburb is the site of Lord\u2019s Cricket Ground?",
        "answers": [
            "St. John's Wood",
            "St John\u2019s Wood",
            "St John's Wood",
            "St John's Wood, London, England",
            "St John's Wood, London",
            "St Johns Wood"
        ]
    },
    {
        "subject": "Brett Favre",
        "question": "What disease was Robert the Bruce, King of Scotland, said to have died of in 1329?",
        "answers": [
            "Midborderline leprosy",
            "Lucio leprosy",
            "Leprocy",
            "Hansenite",
            "Hansen\u2019s disease",
            "Hansenites",
            "Visual surveillance of extremities",
            "Hansens Disease",
            "Leprosy-3 Virus",
            "Leprosey",
            "Hansen's Disease",
            "Leprosy, tuberculoid",
            "Leprosy, indeterminate",
            "Leper hospital",
            "Lucio phenomenon",
            "Upgrading lepra reaction type 1",
            "Lepro-B1 Virus",
            "Lepers",
            "Leprosy, dimorphic",
            "Holdsveiki",
            "Leprosy Virus",
            "Leprosy, borderline lepromatous",
            "Lepracy",
            "Hansen disease",
            "Hansen's disease",
            "Leprosy, Lucio",
            "Leper",
            "Leprosy (Hansen's disease)",
            "Hanson's disease",
            "Leprosy hospital",
            "Lausma",
            "Leprosy, midborderline",
            "Hansons disease",
            "Lepra reaction type 1",
            "Leper hospitals",
            "Leprosy",
            "L\u00edk\u00fer\u00e1",
            "Leperacy",
            "Leprology",
            "Dimorphic leprosy",
            "Downgrading lepra reaction type 1",
            "Likthra",
            "Leprosy, borderline tuberculoid",
            "Leprosy-B Virus",
            "Indeterminate leprosy"
        ]
    },
    {
        "subject": "Brett Favre",
        "question": "Greek philosopher Socrates was sentenced to death by drinking which kind of poison ?",
        "answers": [
            "Hemlock (disambiguation)",
            "Hemlocks",
            "Hemlock",
            "Hemlock, West Virginia",
            "HEMLOCK"
        ]
    },
    {
        "subject": "Brett Favre",
        "question": "Which English word comes from an old French word meaning sour wine?",
        "answers": [
            "White vinegar",
            "Fruit vinegar",
            "Coconut vinegar",
            "\ud83d\udf0b",
            "\ud83d\udf0a",
            "\ud83d\udf0c",
            "Vinager",
            "Vineager",
            "Chili-vinegar",
            "Beer vinegar",
            "Vinegars",
            "Cane vinegar",
            "Vingar",
            "Sukang iloko",
            "Alegar",
            "Vinegar",
            "Red wine vinegar",
            "Spirit vinegar",
            "Sour wine",
            "Honey vinegar",
            "Aceto",
            "Vineger",
            "Thieves vinegar",
            "Malt vinegar",
            "Wine vinegar",
            "Persimmon vinegar"
        ]
    },
    {
        "subject": "Brett Favre",
        "question": "Which country used to be called Southern Rhodesia?",
        "answers": [
            "Zimbobwe",
            "Health care in Zimbabwe",
            "Zimbabwean cultural practices",
            "People of Zimbabwe",
            "Republic of Zimbabwe",
            "Zimbabwean legends",
            "Zimbabwae",
            "Zimbabwian",
            "Republic Of Zimbabwe",
            "Cuisine of Zimbabwe",
            "Zimbabwean cuisine",
            "ZWE",
            "Zimbabwei",
            "Zimbabwe",
            "Etymology of Zimbabwe",
            "ISO 3166-1:ZW",
            "Republic Zimbabwe",
            "Zimbawean",
            "Zimbabwean",
            "Name of Zimbabwe",
            "Chimpabwe"
        ]
    },
    {
        "subject": "Brett Favre",
        "question": "Who was king of Great Britain and Ireland when the American colonies were lost?",
        "answers": [
            "George III, King of Great Britain and Ireland",
            "King george the 3rd",
            "George iii",
            "George III, King of Great Britain",
            "Farmer George",
            "George III of Corsica",
            "GEORGE III",
            "King George 3",
            "King George III",
            "George III of England",
            "George iii of the united kingdom",
            "George III",
            "George III of Great Britain",
            "George III of Scotland",
            "King George III of the United Kingdom",
            "George III of Great Britain and Ireland",
            "George III of Hanover",
            "King George III of Great Britain",
            "George the Third",
            "George III of Britain",
            "George III of the United Kingdom",
            "George III of the UK",
            "George III Guelph",
            "Mad King George",
            "List of titles and honours of King George III",
            "George William Frederick",
            "George III %22the Mad%22 of the United Kingdom",
            "King George 3 of the United Kingdom",
            "George Iii"
        ]
    },
    {
        "subject": "Brett Favre",
        "question": "Which religious figure had a horse named Kanthaka?",
        "answers": [
            "(Guatama)Buddha"
        ]
    },
    {
        "subject": "Brett Favre",
        "question": "As at 2012 Dame Marjorie Scardino is/was head of what high-performing global media/learning corporation?",
        "answers": [
            "Parker Publishing Company, Inc.",
            "S. Pearson & Son",
            "S. Pearson & Sons",
            "Pearson, PLC.",
            "Pearson Vue",
            "Pearson Publishing",
            "Pearson VUE",
            "Infoplease",
            "Infoplease.com",
            "Pearson Group",
            "Pearson PLC",
            "Pearson plc",
            "Pearson Plc",
            "Pearson Communications"
        ]
    },
    {
        "subject": "Brett Favre",
        "question": "In the lyrics of \u2018Hello, Hello, Who\u2019s Your Lady Friend?\u2019, Margate is mentioned in the verse.",
        "answers": [
            "Brighthelmstone",
            "UN/LOCODE:GBBSH",
            "BRIGHTON",
            "Brighton music",
            "Brighton Ferry",
            "Brighton, UK",
            "Brighton, Sussex",
            "Mayor of Brighton",
            "Brighton, East Sussex",
            "Brighton Borough Council",
            "County Borough of Brighton",
            "Brighton, England",
            "Brighton"
        ]
    },
    {
        "subject": "Brett Favre",
        "question": "The bitter 19th century rivalry between paleontologists Edward Drinker Cope and Othniel Charles Marsh during their search for dinosaur fossils is usually described with what 2-words?",
        "answers": [
            "Bone Wars",
            "The Bone Wars",
            "Bone wars",
            "Dinosaur Wars"
        ]
    },
    {
        "subject": "Brett Favre",
        "question": "According to the Kubler-Ross model, what are the 5 stages of grief?",
        "answers": [
            "Denial, Anger, Bargaining, Depression, Acceptance"
        ]
    },
    {
        "subject": "Brett Favre",
        "question": "Which 1988 children\u2019s novel by Roald Dahl features a hostile school headmistress named Miss Trunchbull ?",
        "answers": [
            "MATILDA (Military robot)",
            "MATILDA"
        ]
    },
    {
        "subject": "Brett Favre",
        "question": "\"Who was known as \"\"The Waltz King\"\"?\"",
        "answers": [
            "Strauss jnr",
            "Johann Strauss Jnr.",
            "Johann Strauss, the Son",
            "Johann Strauss, Jnr",
            "Johann Baptist Strauss Jr.",
            "Johann Strauss, II",
            "Johann Strauss, Jr.",
            "Johann Strauss (son)",
            "Johann Strauss The Younger",
            "Johann Strau\u00df (son)",
            "The Waltz King",
            "Johann Strauss II.",
            "Johann strauss ii",
            "Strauss II",
            "Johann Sebastian Strauss",
            "Johann Strau\u00df II",
            "Johann straus",
            "Johan straus ii",
            "Johan strauss ii",
            "Johann Strauss II",
            "Johann Strau\u00df",
            "Johann Strauss, the Younger",
            "Johann strauss",
            "Johan Strauss",
            "Ballets by Johann Strauss II",
            "Johann Strauss Jr",
            "Johann Straus II",
            "Johann Strau\u00df II.",
            "Johann, the Younger Strauss",
            "Strauss junior",
            "J. Strauss II",
            "Johann Strauss Junior",
            "Strauss Waltzes",
            "Johann Strauss Jr.",
            "Johann Strau\u00df the Younger",
            "Strauss the younger",
            "Johann Strauss Jnr",
            "Johann Strauss, Jr",
            "Waltz King",
            "Johann Strauss",
            "Strauss jr",
            "Johann Strauss the Younger"
        ]
    },
    {
        "subject": "Brett Favre",
        "question": "By the year 2010 there were roughly how many bicycles worldwide?",
        "answers": [
            "1billion",
            "one billion",
            "1 billion"
        ]
    },
    {
        "subject": "Brett Favre",
        "question": "Which actor/comedian/quiz presenter was once a professional footballer with Brentford?",
        "answers": [
            "BRADLEY WALSH",
            "Bradley Walsh"
        ]
    },
    {
        "subject": "Brett Favre",
        "question": "In cricket, which nation won the 2009 Ashes series?",
        "answers": [
            "Englnad",
            "The land of the Angles",
            "Sasainn",
            "England, U.K.",
            "Engla land",
            "England's",
            "Starks Field School",
            "Englaland",
            "English Nation",
            "Ingland",
            "Engelond",
            "Englistan",
            "Languages of England",
            "England, UK",
            "Name of England",
            "Auld enemy",
            "Sasana",
            "England, United Kingdom",
            "\u00c6ngland",
            "Lloegr",
            "Land of the Angles",
            "Engla rice",
            "Aengland",
            "UK, (England)",
            "\u00c6nglaland",
            "England",
            "Life in England",
            "Aenglaland",
            "ENGLAND",
            "Anglica",
            "Etymology of England",
            "Pow Sows",
            "\u00c6ngla land"
        ]
    },
    {
        "subject": "Brett Favre",
        "question": "What was the name of the eponymous 'Knight of the Holy Grail' in an opera by Wagner?",
        "answers": [
            "Parcifal",
            "Amfortas",
            "'PARSIFAL'",
            "Parsifal (opera)",
            "Kundry",
            "Parsifal"
        ]
    },
    {
        "subject": "Brett Favre",
        "question": "\"In the TV series, \"\"The Rockford Files\"\", which actor played Rockford's father, \"\"Rocky\"\"?\"",
        "answers": [
            "Noah Beery, Jr.",
            "Noah Beery Jr",
            "NOAH BEERY JR.",
            "Noah Beery Jr.",
            "Noah Beery, Jr"
        ]
    },
    {
        "subject": "Brett Favre",
        "question": "Mr and Mrs Potato Head appear in which film franchise?",
        "answers": [
            "To Infinity and Beyond (catchphrase)",
            "Toy Story (soundtrack)",
            "Toy Story 1",
            "Toy Story (movie)",
            "Toy Story",
            "Toy story",
            "Toystory",
            "A Toy Story",
            "Toy Story 3-D",
            "ToyStory",
            "To Infinity and Beyond",
            "To Infity and Beyond (catchphrase)",
            "Production of Toy Story",
            "You are a toy",
            "Live Action Toy Story"
        ]
    },
    {
        "subject": "Brett Favre",
        "question": "Daniel Casey played the role of Detective Sergeant Troy in which TV series?",
        "answers": [
            "Midsummer Murders",
            "MIDSOMER MURDERS",
            "Detective Sergeant Ben Jones",
            "Midsomer (Fictional county)",
            "MidSomer Murders",
            "Midsomer Murders",
            "Mudsummer murders",
            "Midsomer (fictional county)",
            "Midsommer Murders"
        ]
    },
    {
        "subject": "Brett Favre",
        "question": "What is a honey locust?",
        "answers": [
            "Tree (album)",
            "The Tree",
            "The Trees (song)",
            "Tree maths",
            "Tree (disambiguation)",
            "The Tree (film)",
            "Trees (disambiguation)",
            "The Trees",
            "The Tree (disambiguation)",
            "A TREE"
        ]
    },
    {
        "subject": "Brett Favre",
        "question": "Who preceded Neil Kinnock as leader of the British Labour Party?",
        "answers": [
            "Michael Mackintosh Foot",
            "Foot Heads Arms Body",
            "MICHAEL FOOT",
            "Michael Foot",
            "Agent Boot"
        ]
    },
    {
        "subject": "Brett Favre",
        "question": "In the history of the universe what term refers to immediately after the Big Bang?",
        "answers": [
            "Inflation rate",
            "Ingflation",
            "Economics/Inflation",
            "Causes of inflation in trinidad and tobago",
            "Inflation (prices)",
            "Food inflation",
            "Inflation (economics)",
            "Currency inflation",
            "Price Inflation",
            "Cash inflation",
            "Inflation",
            "Zero inflation",
            "Price inflation",
            "Economic inflation",
            "Threshold Inflation",
            "Effect of inflation",
            "Inflations",
            "Costs of inflation",
            "World inflation crisis",
            "Inflation rates",
            "Inflation (financial)",
            "Causes of inflation in Trinidad and Tobago",
            "Economy/Inflation",
            "Price Trends",
            "Price level stability"
        ]
    },
    {
        "subject": "Brett Favre",
        "question": "Cambridge Favourite is a variety of which fruit?",
        "answers": [
            "Fragaria ananassa",
            "Pineapple strawberry",
            "Fragaria x ananassa",
            "Fragaria \u00d7 ananassa",
            "Culture of strawberry",
            "STRAWBERRY",
            "Fragaria xananassa",
            "Gariguette",
            "Garden strawberries",
            "Garden strawberry",
            "Strawberry",
            "\ud83c\udf53",
            "Strawberries",
            "Ananas strawberry",
            "Strawberrys",
            "Garden Strawberry",
            "Strawberry juice",
            "Strawbarry",
            "Fragaria \u00d7ananassa"
        ]
    },
    {
        "subject": "Brett Favre",
        "question": "Much in the news, who is the Director General of the BBC?",
        "answers": [
            "George Entwistle",
            "GEORGE ENTWISTLE",
            "George Edward Entwhistle",
            "George Entwhistle"
        ]
    },
    {
        "subject": "Brett Favre",
        "question": "Who directed the 2011 Palme d'Or winning film 'The Tree Of Life'?",
        "answers": [
            "Voyage of Time (film)",
            "Terence Malick",
            "Terrence Malick",
            "Terrance Mallick",
            "Terrence malick",
            "Terence malick",
            "Terrence Malik",
            "Terrence Mallick",
            "Terry Malick"
        ]
    },
    {
        "subject": "Brett Favre",
        "question": "In which London thoroughfare is The Monument?",
        "answers": [
            "Pudding Lane"
        ]
    },
    {
        "subject": "Brett Favre",
        "question": "To whom did Helen Keller dedicate her autobiography, The Story of My Life?",
        "answers": [
            "To inventor Alexander Graham Bell, who helped direct her education and considered himself, first and foremost, a teacher of the deaf"
        ]
    },
    {
        "subject": "Brett Favre",
        "question": "At which sport has Indonesia won several medals including gold in each Summer Olympics from 1992-2008?",
        "answers": [
            "Rules of badminton",
            "Badders",
            "Badmitton",
            "Shuttler",
            "Badminton 1000 bc",
            "Badmington",
            "Badmitten",
            "Badminton players",
            "Badminton",
            "Badminton racquet",
            "\ud83c\udff8",
            "Badmiton",
            "History of badminton"
        ]
    },
    {
        "subject": "Brett Favre",
        "question": "Virginia Wade won 4 Women\u2019s Doubles titles at Grand Slam events (but not Wimbledon). Which Australian was her partner each time?",
        "answers": [
            "Margaret Court Smith",
            "MARGARET COURT",
            "Margaret Smith Court",
            "Margaret Court",
            "Victory Life Center",
            "Victory Life Centre",
            "Margaret Jean Court"
        ]
    },
    {
        "subject": "Brett Favre",
        "question": "What was Billy Connolly's only No. 1 hit?",
        "answers": [
            "D-I-V-O-R-C-E"
        ]
    },
    {
        "subject": "Brett Favre",
        "question": "'Baby Come Back' was a number one hit in 1968 for which group, founded by Eddy Grant?",
        "answers": [
            "Equally",
            "Equal (disambiguation)",
            "'THE EQUALS'",
            "Equals (computing)",
            "Equals",
            "The Equals (disambiguation)",
            "Equal",
            "Equals (disambiguation)"
        ]
    },
    {
        "subject": "Brett Favre",
        "question": "Roman Emperor Vespasian came to power in 69AD - the Year of the Four Emperors. Name any of the other three Emperors that year.",
        "answers": [
            "Galba, Otho, Vitellius"
        ]
    },
    {
        "subject": "Brett Favre",
        "question": "Kelly Jones, Richard Jones and Richard Cable founded which group",
        "answers": [
            "Looks Like Chaplin",
            "Stereophonics",
            "The Stereophonics"
        ]
    },
    {
        "subject": "Brett Favre",
        "question": "Horatio was a legendary Roman hero who defended a bridge against which army?",
        "answers": [
            "Etruscan (disambiguation)",
            "Etruscan"
        ]
    },
    {
        "subject": "Brett Favre",
        "question": "Who played the Riddler in the original Batman TV series?",
        "answers": [
            "Gorshin",
            "Frank Gorshin",
            "FRANK GORSHIN"
        ]
    },
    {
        "subject": "Brett Favre",
        "question": "\"\"\"The Great Gate of Kiev\"\" and \"\"Catacombs\"\" are two sections of which musical work by Mussorgsky?\"",
        "answers": [
            "Bilder einer Ausstellung",
            "The Great Gate of Kiev",
            "Pictures at an Exhibition",
            "Pictures from an Exhibition",
            "Pictures At An Exhibition",
            "The great gate of kiev",
            "PICTURES AT AN EXHIBITION",
            "Kartinkis Vistavski",
            "Promenade (Pictures at an Exhibition)",
            "Great Gate of Kiev",
            "Pictures at an exhibition"
        ]
    },
    {
        "subject": "Brett Favre",
        "question": "The Sandinista National Liberation Front ruled from 1979 to 1990, initially as part of a Junta of National Reconstruction, in which country?",
        "answers": [
            "Nicarugua",
            "Nicuragua",
            "Administrative divisions of Nicaragua",
            "Bibliography of nicaragua",
            "Subdivisions of Nicaragua",
            "Health in Nicaragua",
            "Republica De Nicaragua",
            "Etymology of Nicaragua",
            "Rep\u00fablica de Nicaragua",
            "Sport in Nicaragua",
            "ISO 3166-1:NI",
            "Republic of Nicaragua",
            "The Republic of Nicaragua",
            "Nicaraguan",
            "Nicaragua",
            "Nicaragua, Central America"
        ]
    },
    {
        "subject": "Brett Favre",
        "question": "In British legend, what is the name of King Arthur\u2019s sword?",
        "answers": [
            "Rhongomiant",
            "Excalibur",
            "Clarent",
            "Caledvwlch",
            "XCalibur",
            "Sword in the stone (King Arthur)",
            "Excalibvr",
            "Excaliber",
            "Caledfwlch",
            "Caliburn",
            "Caladfwlch"
        ]
    },
    {
        "subject": "Brett Favre",
        "question": "Which 18th century polymath invented the lightning rod, the flexible urinary catheter, and coined the phrase 'time is money'?",
        "answers": [
            "A Tradesman of Philidelphia",
            "Bin Franklin",
            "Abigail Afterwit",
            "The Busybody",
            "Anthony Afterwit",
            "Betty Diligent",
            "Benjamin Franklin",
            "The Benjamin Franklin",
            "Franklinian",
            "Friend to the Poor",
            "Ben Franlkin",
            "Bejamin franklin",
            "Alice Addertongue",
            "Sage of the Constitutional Convention",
            "Franklinic",
            "Benjamin franklin",
            "Those who would give up Essential Liberty",
            "Ben Franklin",
            "B franklin",
            "The Benjamin Franklin Bust",
            "B. Franklin",
            "Abigail Twitterfield",
            "Benjamin (Ben) Franklin",
            "Ben franklin",
            "Sidi Mehemet Ibrahim",
            "B Franklin"
        ]
    },
    {
        "subject": "Brett Favre",
        "question": "What is the largest city and capital of Madeira?",
        "answers": [
            "Funchal",
            "Funchal, Madeira",
            "Funchal, Madeira Islands"
        ]
    },
    {
        "subject": "Brett Favre",
        "question": "What model of Ford was named after a city in Southern Spain",
        "answers": [
            "Granada",
            "UN/LOCODE:ESGRX",
            "Illiberi Liberini",
            "Granada (city)",
            "Eliberri",
            "Elibyrge",
            "Ilbira",
            "Elybirge",
            "Granada, Granada",
            "Granada, Spain",
            "The weather in Granada",
            "Illiber"
        ]
    },
    {
        "subject": "Brett Favre",
        "question": "Alan Bates played an escaped convict who was mistaken for the son of God in which 1961 film?",
        "answers": [
            "Whistle down the Wind",
            "Whistle Down The Wind",
            "Whistle Down the Wind (disambiguation)",
            "Whistle Down the Wind"
        ]
    },
    {
        "subject": "Brett Favre",
        "question": "Which river flows through Cologne?",
        "answers": [
            "Rhine",
            "Alpenrhein River",
            "Rhinen",
            "Rhine Estuary",
            "Rhinewater",
            "River Rhein",
            "The Rhine",
            "Upper Rhine River Plains",
            "Rhein River",
            "Rhine river",
            "Rhine basin",
            "Rhine River",
            "Rhine (river)",
            "Rhein (river)",
            "Rhine mouth",
            "Rijn",
            "River Rhine Pollution: November 1986",
            "Length of the Rhine",
            "Rayn",
            "River Rhine"
        ]
    },
    {
        "subject": "Brett Favre",
        "question": "In popular music how is Paul Hewson better known?",
        "answers": [
            "Paul Hewson",
            "Bono Vox",
            "Bono (U2)",
            "Paul David Hewson",
            "BONO",
            "Bono"
        ]
    },
    {
        "subject": "Brett Favre",
        "question": "Didsbury, Ardwick and Fallowfield are all areas of which British city?",
        "answers": [
            "Manchester developments",
            "Manchester (borough)",
            "UN/LOCODE:GBMNC",
            "Manchester, Greater Manchester",
            "Manchester, UK",
            "Climate of Manchester",
            "City of Manchester",
            "The weather in Manchester",
            "Manchester (city, England)",
            "Machester",
            "Drizzlechester",
            "Mancs",
            "Manchester",
            "Manchester, United Kingdom",
            "Manchester (England)",
            "Metropolitan Borough of Manchester",
            "Manchester, U.K.",
            "Manchester (UK)",
            "England Manchester",
            "Manchester, England",
            "County Borough of Manchester"
        ]
    },
    {
        "subject": "Brett Favre",
        "question": "For which two films has Michael Caine won Oscars?",
        "answers": [
            "\"\"\"The Cider House Rules\"\" & \"\"Hannah and Her Sisters\"\"\""
        ]
    },
    {
        "subject": "Brett Favre",
        "question": "What is the nickname of the Australian national rugby union team?",
        "answers": [
            "Wallabies Rugby Team",
            "Australia rugby union team",
            "Australia national rugby union team",
            "Qantas Wallabies",
            "The Australian national rugby union team",
            "The Wallabies",
            "Australian National Rugby Union Team",
            "Australia national rugby union side",
            "Wallabies",
            "Australian rugby union team",
            "Australia National Rugby Union Team",
            "Australian Wallabies",
            "Australian national rugby union team"
        ]
    },
    {
        "subject": "Brett Favre",
        "question": "Which motorcycle company introduced the Jet Ski in 1972?",
        "answers": [
            "Kawasockie",
            "Kawasaki (disambiguation)",
            "Kawasaki"
        ]
    },
    {
        "subject": "Brett Favre",
        "question": "Which French painter was known as 'Le Douanier' because of his job as a customs official?",
        "answers": [
            "Henri Julien F\u00e9lix Rousseau",
            "Henri rousseau",
            "Henri Rousseau (1844-1910)",
            "Rousseau, Henri Julien F\u00e9lix",
            "Henri Julien Felix Rousseau",
            "The Magnificant Paintings of Henri Rousseau",
            "Henri Rousseau",
            "Le Douanier Rousseau",
            "Rousseau, Henri Julien Felix",
            "(Henri) Rousseau",
            "Henri-Julien-F\u00e9lix Rousseau"
        ]
    },
    {
        "subject": "Brett Favre",
        "question": "Conventionally treated as comprising a single order, which order of mammals lay eggs?",
        "answers": [
            "Fossil Monotremes",
            "Ornithodelphia",
            "Egg laying mammals",
            "Manotremata",
            "Monotrememata",
            "Monotremes",
            "Protherians",
            "Monotreme",
            "Egg-laying mammal",
            "Egg-laying mammals",
            "Monotramata",
            "Monotremata",
            "Egg laying mammal"
        ]
    },
    {
        "subject": "Brett Favre",
        "question": "Where is the world's widest street?",
        "answers": [
            "Buenos Aires (Argentina)",
            "Bs As",
            "Buenos",
            "Ciudad Autonoma de Buenos Aires",
            "Buenos Aires Autonomous City",
            "Buenos-Aires",
            "Buenos aires",
            "Buenos Aires, Argentina",
            "City of Buenos Aires",
            "UN/LOCODE:ARBUE",
            "La Reina del Plata",
            "AR-C",
            "Demographics of Buenos Aires",
            "History of Buenos Aires",
            "Buenos Aires",
            "BsAs",
            "Autonomous city of Buenos Aires",
            "Baires",
            "B Aires",
            "Buenos Aires Capital Federal",
            "Buenos A\u00edres",
            "Ciudad Aut\u00f3noma de Buenos Aires",
            "Regina Theatre",
            "Capital Federal, Argentina",
            "BBAA",
            "Buenos Aries",
            "Autonomous City of Buenos Aires",
            "Ciudad de Buenos Aires",
            "Buenos Aires City",
            "Bs. As.",
            "B. Aires",
            "Distrito Federal, Argentina",
            "Bs as",
            "Capital federal (Argentina)",
            "Bs.As.",
            "Buenos Ares",
            "Capital of Argentina",
            "Capital federal, Argentina",
            "Capital federal",
            "Paris of South America",
            "Buenos Aires city",
            "Buenoes Ayres"
        ]
    },
    {
        "subject": "Brett Favre",
        "question": "\"What was the first pop video directed by John Landis, whose directing credits include \"\"National Lampoon's Animal House\"\" and \"\"The Blues Brothers\"\"?\"",
        "answers": [
            "\"Michael Jackson's \"\"Thriller\"\"\"",
            "Michael Jackson's Thriller",
            "Michael jackson thriller",
            "Michael Jackson's Thriller (disambiguation)",
            "Michael Jacksons Thriller"
        ]
    },
    {
        "subject": "Brett Favre",
        "question": "Which American city has districts called Financial, Mission, Japantown and Richmond?",
        "answers": [
            "San Fransciso",
            "San francisco radio stations",
            "The weather in San Francisco",
            "San Fransisco, California",
            "San Francisco (City and County)",
            "Baghdad by the Bay",
            "San Francisco County, California",
            "San Francisco, CA, United States",
            "More reading about San Francisco",
            "San Franciscan",
            "Friscoe",
            "San Francisco",
            "Sanfracisco",
            "San Franciscans",
            "San Francisco, Calif",
            "San-Fransisco",
            "City & County of San Francisco",
            "Old Gold Mountain",
            "San Francisco County, CA",
            "San Francisco, California, U.S.",
            "San Fransisco CA",
            "San Francisco county",
            "San Francisco County",
            "Sanchez Street",
            "San Francisco (county)",
            "San Francisco City and County",
            "City by the bay",
            "San Pancho",
            "Climate of San Francisco",
            "San-Francisco",
            "San Francisco, California, United States",
            "San Francisco, California, USA",
            "San Fran",
            "San Francisco (Calif.)",
            "McLaren, California",
            "San Francisco, California",
            "San Francisco, CA.",
            "Radio stations in san francisco",
            "San Fransico County, California",
            "City by the Bay",
            "The City by the Bay",
            "San Francisco, Calif.",
            "Demographics of San Francisco",
            "San Francisco, United States of America",
            "County of San Francisco",
            "The Hamlin School",
            "San Francisco, CA",
            "San Francisco, California, U.S.A.",
            "UN/LOCODE:USSFO",
            "San Francisco, US-CA",
            "San francisco, ca",
            "San Francisco CA",
            "City of San Francisco, California",
            "San Francisco (CA)",
            "San Fran, California",
            "City and County of San Francisco, California",
            "San Fransico, California",
            "San francisco, CA",
            "San Franscisco",
            "City of San Francisco",
            "County of San Francisco, California",
            "SF, CA",
            "San Francisco, California, US",
            "San Franciso",
            "San Fransisco",
            "Baking Arts",
            "San Francisco, USA",
            "Crime in San Francisco",
            "City and County of San Francisco",
            "San Francisco, United States",
            "San Francisco, Ca",
            "The City That Knows How",
            "San francisco",
            "McKinley Elementary School San Francisco",
            "San Fransisco, CA",
            "San Fransico"
        ]
    },
    {
        "subject": "Brett Favre",
        "question": "Red Grant was a villain in which James Bond movie?",
        "answers": [
            "From Russia With Love (album)",
            "From Russia with Love (album)",
            "From Russia, With Love",
            "From Russia with Love (disambiguation)",
            "James Bond/From Russia With Love",
            "From russia with love",
            "From Russia With Love",
            "From Russia, with Love",
            "From Russia with Love"
        ]
    },
    {
        "subject": "Brett Favre",
        "question": "Which principality was established in 1278 by the Treaty of Joint Suzerainty?",
        "answers": [
            "Military of Andorra",
            "Principado de Andorra",
            "Valles de Andorra",
            "ANDORRA",
            "Andorra",
            "The Principality of Andorra",
            "Name of Andorra",
            "Health in Andorra",
            "Religion in Andorra",
            "AndorrA",
            "Protestantism in Andorra",
            "The weather in Andorra",
            "Andorre",
            "Principaut\u00e9 d'Andorre",
            "Hinduism in Andorra",
            "Andorra/Military",
            "Andorran Navy",
            "Principaute d'Andorre",
            "Principat d'Andorra",
            "Principality of Andorra",
            "ISO 3166-1:AD"
        ]
    },
    {
        "subject": "Brett Favre",
        "question": "Who did Joe Louis beat to take the world heavyweight boxing title in 1937?",
        "answers": [
            "James Braddock",
            "Braddock, James",
            "James Braddock (disambiguation)",
            "Jim Braddock"
        ]
    },
    {
        "subject": "Brett Favre",
        "question": "Who was the leader of France\u2019s Vichy Government during World War II?",
        "answers": [
            "Henri Phillippe P\u00e9tain",
            "Philippe Benoni Omer Joseph Petain",
            "Philip Petain",
            "Marshal P\u00e9tain",
            "Petain",
            "Phillippe P\u00e9tain",
            "Philipp Petain",
            "Philipe Petain",
            "Marshal Petain",
            "Henri-Philippe Petain",
            "General P\u00e9tain",
            "Henri-Philippe P\u00e9tain",
            "Phillippe Petain",
            "Marshal philippe petain",
            "Philippe Benoni Omer Joseph P\u00e9tain",
            "Henri Phillippe Petain",
            "Petainist",
            "Mar\u00e9chal P\u00e9tain",
            "Philipe P\u00e9tain",
            "Henri Philippe Benoni Omer Joseph Petain",
            "Marshal Philippe Petain",
            "Marshal Henri Philippe Petain",
            "Marshall Petain",
            "Marshall P\u00e9tain",
            "Henri Philippe Petain",
            "Henri Philippe Benoni Omer Joseph P\u00e9tain",
            "Phillipp P\u00e9tain",
            "Henri Philippe P\u00e9tain",
            "Henri Petain",
            "Marshal Henri Petain",
            "Marechal Petain",
            "Phillipp Petain",
            "P\u00e9tainisme",
            "Philipp P\u00e9tain",
            "Philippe P\u00e9tain",
            "P\u00e9tain",
            "Philip P\u00e9tain",
            "Phillip P\u00e9tain",
            "General Petain",
            "Phillip Petain",
            "Henri P\u00e9tain",
            "Phillipe P\u00e9tain",
            "Philippe Petain",
            "Phillipe Petain",
            "Petainisme"
        ]
    },
    {
        "subject": "Brett Favre",
        "question": "Which word completes Interatrial _______ and Interventricular ________ which are the walls of tissue separating the chambers on the left and right of the heart?",
        "answers": [
            "Septum (anatomy)",
            "SEPTUM",
            "Heart septum",
            "Septal",
            "Aseptate",
            "Septae",
            "Cardiac septa",
            "Septum"
        ]
    },
    {
        "subject": "Brett Favre",
        "question": "In a game of professional soccer, a red card is used to indicate that a player has been what?",
        "answers": [
            "Sent of the field of play and cannot be replaced"
        ]
    },
    {
        "subject": "Brett Favre",
        "question": "\"What song is this lyric from: \"\"Driver at the engine, fireman rings the bell, sandman swings the lantern to show that all is well\"\"?\"",
        "answers": [
            "Morningtown Ride"
        ]
    },
    {
        "subject": "Brett Favre",
        "question": "\"Which political philosopher wrote \"\"The Theory of Moral Sentiments\"\" and \"\"An Inquiry into the Nature and Causes of the Wealth of Nations\"\"?\"",
        "answers": [
            "Vile maxim",
            "A Smith",
            "Adam Smith",
            "Adam smith"
        ]
    },
    {
        "subject": "Brett Favre",
        "question": "What is the longest time that there can be between General Elections in the UK?",
        "answers": [
            "5 years",
            "five  time",
            "5 time"
        ]
    },
    {
        "subject": "Brett Favre",
        "question": "\"Who was the male half of \"\"Bennifer\"\"?\"",
        "answers": [
            "Political views of Ben Affleck",
            "Nathan Decker",
            "Ben Affleck",
            "Tell No One (2014 film)",
            "Benjamin Geza Affleckbold",
            "B. G. Affleck-Boldt",
            "Ben Afflek",
            "Ben affleck",
            "Line of Sight (film)",
            "Benjamin G. Affleckbold",
            "Benjamin Geza Affleck-Boldt",
            "Benjamin G. Affleck-Boldt",
            "Benjamin G. Affleck",
            "Ben Afleck",
            "Benjamin Geza Affleck",
            "Benjamin Affleck",
            "Affleck, Ben",
            "Ben Aflek",
            "Ben Affleck-Boldt",
            "Filmography of Ben Affleck",
            "Ben aflect",
            "Nathan Decker (film)",
            "Benjamin G\u00e9za Affleck-Boldt",
            "Benjamin G\u00e9za Affleck"
        ]
    },
    {
        "subject": "Brett Favre",
        "question": "In fashion, Hobble, Pencil and Dirndl are all types of what?",
        "answers": [
            "Broomstick skirt",
            "Midi-skirt",
            "Skirted",
            "Short skirted",
            "Lahenga",
            "Tiered skirt",
            "Short-skirted",
            "Skirt (garment)",
            "Winter skirt",
            "Short skirt",
            "Maxi-skirt",
            "Slim skirt",
            "Bubble dress",
            "Circular skirt",
            "Maxiskirt",
            "Afternoon skirt",
            "Maxi skirt",
            "Midi skirt",
            "Skirts",
            "Long skirted",
            "Long-skirted",
            "Long skirt",
            "Bell skirt",
            "Skirt",
            "Midiskirt"
        ]
    },
    {
        "subject": "Brett Favre",
        "question": "Who played the character Mr Chips in the 2002 TV adaptation of Goodbye Mr Chips",
        "answers": [
            "Philippa Braithwaite",
            "Lucy Aston",
            "Martin Clunes"
        ]
    },
    {
        "subject": "Brett Favre",
        "question": "Cobweb is a fairy in which Shakespeare play?",
        "answers": [
            "A midsummer night's dream",
            "A Midsummer Night's dream",
            "Demetrius (A Midsummer Night's Dream)",
            "A Midsummer Nights' Dream",
            "Lysander (Midsummer Night Dream)",
            "A midsummer's dream",
            "A mid summer night's dream",
            "Pease-blossom",
            "A Midsummer Night's Dream",
            "A Midsummernight's Dream",
            "Incidental Music to A Midsummer Night's Dream",
            "Peaseblossom",
            "AMND",
            "A Midsummer Night'S Dream",
            "Hermia and Helena",
            "Midsummer Night\u2019s Dream",
            "A Midsummer Night\u2019s Dream",
            "Midsummer Nights Dream",
            "Hippolyta (Shakespeare)",
            "Midsummer Night's Dream",
            "A Midsommer Nights Dreame",
            "A Midsummer Nights Dream",
            "Midsummer nights dream",
            "Lysander (Shakespeare)",
            "The Rude Mechanicals",
            "A Midsummer Night's Dream, Act IV",
            "Rude Mechanic",
            "A Midsummer's Night Dream",
            "Lysander (A Midsummer Night's Dream)",
            "A midsummernight's dream",
            "A Midsummer-Night's Dream",
            "Midsummer-Night's Dream",
            "A Mid\u017fommer Nights Dreame",
            "Demetrius (Midsummer Night Dream)",
            "Midsummer night dream",
            "A Middsummer Night's Dream",
            "MSND"
        ]
    },
    {
        "subject": "Brett Favre",
        "question": "\"Didier Delsalle who wrote the following words confirming his May 14, 2005 achievement became the first person to land a helicopter where? \"\"No, nobody went out of the helicopter as I was alone and quite busy to stabilize the helicopter on this windy ...! The terrain characteristics prevent any full landing on the ... as you can see on the videos and only a hover landing...\"\"\"",
        "answers": [
            "Summit of Mount Everest"
        ]
    },
    {
        "subject": "Brett Favre",
        "question": "Of the ten most populated cities of the USA which is furthest north?",
        "answers": [
            "The 313",
            "Detroit, Michigan",
            "2014 Southeastern Michigan flood",
            "Detroit, Mich.",
            "West Side Detroit",
            "Detroit, Michigan, United States",
            "The weather in Detroit",
            "State of Detroit",
            "Detroit automaker",
            "St. Scholastica School, Detroit",
            "Detroit, MI",
            "Detroit, USA",
            "Detroit, Michigan, U.S.",
            "Detroit, Michigan, US",
            "Demographics of Detroit",
            "Detroit (MI)",
            "Motor city",
            "UN/LOCODE:USDET",
            "Racial and Ethnic History of Detroit",
            "Demographics of Detriot",
            "Detroit, M.I.",
            "Detroit, Michigan, USA",
            "Race and ethnicity in Detroit",
            "The Motor City",
            "Motown, Michigan",
            "The 3-1-3",
            "D\u00e9troit, MI",
            "Detroit, mi",
            "Detroit's Effort in the Great War",
            "Detroit",
            "Detroit, United States",
            "Detroit, Michigan, U.S.A.",
            "The motor city",
            "Detroiters",
            "Detroit Michigan",
            "City of Detroit",
            "City of Detroit, Michigan",
            "Detroit City",
            "Motor City",
            "East Side Detroit",
            "Detroit MI",
            "Demographic profile of Detroit",
            "Detroit (Mich.)",
            "Detriot",
            "D\u00e9troit, Michigan"
        ]
    },
    {
        "subject": "Brett Favre",
        "question": "Which English writer died on the same day as Spanish writer 'Miguel de Cervantes' in 1616?",
        "answers": [
            "Shakspeare",
            "W Shakespeare",
            "The Bard of Avon",
            "VVilliam Shake\u1d98peare",
            "William Shakepeare",
            "Shakespearean",
            "Wm. Shakespeare",
            "William shekspere",
            "Shakespeare",
            "William Shake-speare",
            "VViliam shakespeare",
            "Swan of Avon",
            "VVilliam Shake\u017fpeare",
            "Wiliiam shakespear",
            "Billy Shakes",
            "Shakespears",
            "Shakespire",
            "Shakespearian",
            "Will Shakespeare",
            "W. Shakespeare",
            "Shake\u017fpeare",
            "William Shakspeare",
            "William Shakespeare",
            "William Shakespear",
            "Shakespare",
            "William Shakespeare biography",
            "Bill Shakespear",
            "Shakespere",
            "Shakespeare's",
            "Shakespearean theatre",
            "William shakespare",
            "Bill Shakespeare",
            "Sheikh Zubeir",
            "Shakespeere",
            "William shakspeare",
            "Shakesepere",
            "William shakespeare",
            "William Skakespeare",
            "William Shakspere",
            "Shakespeare's biography",
            "Shakesphere",
            "Shakespeares",
            "William shakesphere",
            "Shake-speare",
            "Shakespeare, Wm",
            "William Shakespere",
            "WilliamShakespeare",
            "Shakspere, William",
            "Willaim shakespear",
            "Bard of Avon",
            "Sweet Swan of Avon",
            "Shakespearian Literature",
            "Shakespeareana",
            "Shake speare",
            "Shakesepare",
            "History of Shakespearan art",
            "Gulielmus Shakspere",
            "William Shakespeare's"
        ]
    },
    {
        "subject": "Brett Favre",
        "question": "Hafidh are people who have memorized what?",
        "answers": [
            "Curaan",
            "Final Testament",
            "Arabic Quran",
            "Ghoran",
            "\u0642\u0648\u0631\u0626\u0627\u0646",
            "Quaran",
            "The Noble Qur'an",
            "Qur\u02bc\u0101n",
            "Koraan",
            "Quraan",
            "Qur\u02bb\u0101n",
            "Qur'An",
            "Qur%60an",
            "Qur\u2019\u0101n",
            "The Qur'an",
            "Qora'an",
            "Al-Qur'an",
            "Qur'aan",
            "Al-Quran",
            "The Koran",
            "The Holy Qur'an",
            "The Quran",
            "Quran",
            "Qu'ranic",
            "Qora\u2019an",
            "Quram",
            "\u0627\u0644\u0642\u0631\u0622\u0646",
            "Koranic",
            "Al-Qur'\u0101n",
            "Qur\u02bcan",
            "About Holy Quran",
            "Qur'\u00e1n",
            "Qur\u00e1n",
            "Qur\u2019an",
            "Qur'anic",
            "Qur'an",
            "Qur'an al Karim",
            "Holy Qur'an",
            "Qur\u02be\u0101n",
            "Holy Quran",
            "Mother Book",
            "Qur\u2019anic",
            "Qoraan",
            "The quran",
            "Al Quran",
            "Alcoran",
            "Qran",
            "Qur'\u00e2n",
            "Qura'an",
            "Kalaam-e-majeed",
            "Quar'an",
            "Qoran",
            "Qur'\u0101n",
            "Holy Koran",
            "Murattal",
            "Al-Qur\u2019\u0101n",
            "Qur\u02bean",
            "Qu'ran",
            "Noble qu'ran",
            "Al-Qur\u0101n",
            "Qu\u2019ran",
            "Koran",
            "Quoran",
            "Holy Qu-ran",
            "The Holy Quran",
            "Final testament",
            "The Holy Koran",
            "Glorious Qur'an",
            "Korans",
            "Al-Coran",
            "Qur\u00e2n",
            "Quranic",
            "Kor\u0101n",
            "QURAN",
            "Ko'ran",
            "The Holy Qoran",
            "Al-Quran al-karim",
            "Qur'\u00e0n",
            "Qur\u2019aan",
            "Koran al Karim",
            "TheKoran",
            "Al Koran al Karim",
            "Qur\u00b4an"
        ]
    },
    {
        "subject": "Brett Favre",
        "question": "What is Donald Duck's middle name",
        "answers": [
            "Fauntleroy",
            "Little Lord Fauntleroy (film)",
            "Lord Fauntleroy",
            "Little Lord Fontleroy",
            "Little Lord Fauntleroy"
        ]
    },
    {
        "subject": "Brett Favre",
        "question": "In the UK television series \u2018Doctor Who\u2019, in which country was ruthless politician Salamander born?",
        "answers": [
            "Mexican Republic",
            "MEXICO",
            "Estados Unidos de M\u00e9xico",
            "Sierra de la Estrella",
            "Mexico (country)",
            "Mexic\u00f3",
            "The United Mexican States",
            "Estados Unidos de Mexico",
            "Central Mexico",
            "ISO 3166-1:MX",
            "Mexiko",
            "M\u00e9jico",
            "Mexique",
            "Mexican United States",
            "Mexican'",
            "The United State of Mexico",
            "Mountains of Mexico",
            "Old Mexico",
            "United states of mexico",
            "EUM",
            "Messico",
            "Mejico",
            "The United States of Mexicans",
            "Untied Mexican States",
            "M\u00e9xico",
            "Etymology of Mexico",
            "Meixcan",
            "Estados Unidos Mexicanos",
            "Mexic",
            "Mexxico",
            "Mexican Union",
            "The United States of Mexico",
            "United State of Mexico",
            "Mexico",
            "Republic of Mexico",
            "Mexican Federal Republic",
            "United Mexican States",
            "Mexican coast",
            "Mehico",
            "United States of Mexicans",
            "United States of Mexico"
        ]
    },
    {
        "subject": "Brett Favre",
        "question": "Who coached New Zealand when they won the 2011 Rugby Union World Cup?",
        "answers": [
            "Graham Henry",
            "GRAHAM HENRY",
            "Sir Graham Henry"
        ]
    },
    {
        "subject": "Brett Favre",
        "question": "Who was the main female singer with the groups Jefferson Airplane, Jefferson Starship and Starship?",
        "answers": [
            "Grace Slick",
            "Grace Wing",
            "Grace Barnett Wing"
        ]
    },
    {
        "subject": "Brett Favre",
        "question": "Who partnered Jo Durie when she won the Wimbledon mixed doubles title in 1987?",
        "answers": [
            "Jeremy Bates (disambiguation)",
            "Jeremy Bates"
        ]
    },
    {
        "subject": "Brett Favre",
        "question": "The Battle of the Plains of Abraham in 1759, a pivotal battle in the Seven Years' War fought between the English and the French, is the only major confrontation ever to have taken place in what country?",
        "answers": [
            "Canada",
            "Canad\u00e1",
            "The Dominion of Canada",
            "Commonwealth of Canada",
            "Dominion of canada",
            "ISO 3166-1:CA",
            "Etymology of Canada",
            "CANADA",
            "Canadiophile",
            "Canada's",
            "\u1472\u14c7\u1455",
            "Canada/References",
            "America's top hat",
            "Canada.",
            "Cnada",
            "\u010canada",
            "Canadian Federation",
            "Kenadian",
            "Canadialand",
            "Xanada",
            "Dominion of Canada",
            "Canadaa"
        ]
    },
    {
        "subject": "Brett Favre",
        "question": "Which South African soldier / statesman fought against the British in the Boer War, then on the side of the allies in both World Wars, and was instrumental in the founding of the League of Nations in 1919?",
        "answers": [
            "JAN SMUTS",
            "Jan Christiaan Smuts",
            "General Smuts",
            "General Jan Smuts",
            "Jan Christiaan Smuts of South Africa",
            "Jan C. Smuts",
            "Ian Smuts",
            "J. C. Smuts",
            "Field Marshal Smuts",
            "J C Smuts",
            "J.C. Smuts",
            "Jan Smuts",
            "Jan Christian Smuts",
            "Smuts",
            "Jan smuts",
            "JC Smuts"
        ]
    },
    {
        "subject": "Brett Favre",
        "question": "Which Italian sauce for pasta contains tomato, black olives, capers, anchovies and red peppers? The name translates as 'whore\u2019s style'?",
        "answers": [
            "Sugo alla puttanesca",
            "Spaghetti alla puttanesca",
            "Puttenesca",
            "Pettenesca",
            "Pasta Puttanesca",
            "Putanesca",
            "Pasta alla Puttanesca",
            "Puttanesca",
            "Salsa puttanesca",
            "Spaghetti alla Puttanesca",
            "Pasta alla puttanesca"
        ]
    },
    {
        "subject": "Brett Favre",
        "question": "With what possession can Wonder Woman force people to tell the truth?",
        "answers": [
            "Riata",
            "Lassoo",
            "Uurga",
            "Reata",
            "Lasoo",
            "Lasso"
        ]
    },
    {
        "subject": "Brett Favre",
        "question": "What was the former name of The Home Guard",
        "answers": [
            "Local Defence Volunteers",
            "Home Guard (United Kingdom)",
            "British Home Guard"
        ]
    },
    {
        "subject": "Brett Favre",
        "question": "What is the name of the plastic bit on the end of shoelaces?",
        "answers": [
            "Anglets",
            "An aglet",
            "Fluglebinder",
            "Flugelbinder",
            "Agnet",
            "Aglet"
        ]
    },
    {
        "subject": "Brett Favre",
        "question": "\"In economics, whose law states that, \"\"Bad Money Drives Out Good\"\"?\"",
        "answers": [
            "Thomas Gresham",
            "Sir Thomas Gresham",
            "SIR THOMAS GRESHAM"
        ]
    },
    {
        "subject": "Brett Favre",
        "question": "Which Norwegian explorer was the founder of the Nordic settlement in Greenland in the 10th century?",
        "answers": [
            "Eystribyggd",
            "Eir\u00edkr rau\u00f0i",
            "Eir\u00edkr Thorvaldsson",
            "Erik the Red",
            "Eir\u00edkr Rau\u00f0i",
            "Erik the red",
            "Erik The Red",
            "ERIK THE RED",
            "Eirikr Raudi",
            "Eric the Red",
            "Eric the Red's",
            "Eirikr Thorvaldsson",
            "Eric The Red",
            "Eirik Raude",
            "Eric Raude",
            "Eirikur Raudi",
            "Eir\u00edkur Rau\u00f0i",
            "Eir\u012bkr \u00de\u014drvaldsson",
            "Eirikr raudi",
            "Eric the red",
            "Eric the Red-haired"
        ]
    },
    {
        "subject": "Brett Favre",
        "question": "First debuting in the cartoon Mickey's Review, what classic turtle neck wearing cartoon character had the original name of Dippy Dog?",
        "answers": [
            "Goofy holler",
            "Goofey",
            "Gawrsh!",
            "Goofy Jr.",
            "George Geef",
            "Max Goofy",
            "Goofy yell",
            "Ah-Hyuck",
            "Goofy",
            "Ah-hyuck",
            "A-Hyuck",
            "Goofy Goof",
            "Goofy Sr.",
            "Dippy Dawg",
            "Super Goofy",
            "Super Goof",
            "Goofy filmography",
            "List of Goofy Cartoons",
            "A-hyuck",
            "List of Donald Duck & Goofy Cartoons"
        ]
    },
    {
        "subject": "Brett Favre",
        "question": "What modern narrative got its lease of life when editor Lee Salem heard his 8-yr son say it was like Doonesbury for kids when he was about to reject it for being too-literate/too-adult?",
        "answers": [
            "Calvin and Hobbes by Bill Watterson"
        ]
    },
    {
        "subject": "Brett Favre",
        "question": "What is the most populated city in America?",
        "answers": [
            "New Yourk State",
            "State of N.Y.",
            "US-NY",
            "N Y",
            "The state of NY",
            "NewYork",
            "NYS",
            "Neo York",
            "NY state",
            "Nova York",
            "State of new york",
            "Ny",
            "New york",
            "Nueva York (estado)",
            "N Y state",
            "New York (state)",
            "U.S. state of New York",
            "New York state",
            "New York, U.S.",
            "State New York",
            "N\u00fdja-J\u00f3rv\u00edk",
            "Newyork",
            "NEW YORK",
            "State of N. Y.",
            "N. Y. state",
            "NY",
            "The state of N.Y.",
            "NY (state)",
            "New York's",
            "N.Y. (U.S. state)",
            "State of new yourk",
            "New York State",
            "New York (U.S. state)",
            "New york state",
            "New Yrok",
            "11th State",
            "New York (USA State)",
            "State of N Y",
            "New-York",
            "The State of New York",
            "State of New York",
            "US state of New York",
            "N Y (U.S. state)",
            "N.Y. state",
            "N.Y.",
            "The state of N. Y.",
            "N. Y. (state)",
            "The state of N Y",
            "New York, US",
            "N.Y. (state)",
            "Nyja-Jorvik",
            "Religion in New York",
            "New Yourk",
            "N. Y.",
            "New York State's",
            "Estado Nueva York",
            "New York (USA state)",
            "New york population",
            "New York, U.S.A",
            "New York",
            "NY (U.S. state)",
            "Estado de Nueva York",
            "N. Y. (U.S. state)",
            "Eleventh State",
            "N Y (state)",
            "State of NY",
            "New York (State)",
            "New York (U.S. state"
        ]
    },
    {
        "subject": "Brett Favre",
        "question": "The name of which European capital city means Merchants Harbour?",
        "answers": [
            "K\u00f8benhavn, Denmark",
            "K-Town, Copenhagen",
            "UN/LOCODE:DKCPH",
            "Copenhagen, Denmark",
            "Koepenhamn",
            "K-Town Hardcore",
            "Capital of Denmark",
            "Ktown Hardcore",
            "Copenhague",
            "Kaupmannah\u00f6fn",
            "Kaupmannahofn",
            "Kopenhamn",
            "Koebenhavn",
            "K Town Hardcore",
            "K\u00f6penhamn",
            "COPENHAGEN",
            "Kopenhagen",
            "K\u00f8benhavn",
            "Hafnia (Latin)",
            "Kj\u00f8benhavn",
            "K Town punk",
            "Kobenhavn",
            "Copenhagen (Denmark)",
            "K-Town punk",
            "Copenhagen",
            "DKCPH"
        ]
    },
    {
        "subject": "Brett Favre",
        "question": "Who composed the opera `L'Elisir d'Amore'?",
        "answers": [
            "GAETANO DONIZETTTI"
        ]
    },
    {
        "subject": "Brett Favre",
        "question": "Which Scottish newspaper features the Broons and Oor Wullie?",
        "answers": [
            "Sunday Post",
            "The Sunday Post"
        ]
    },
    {
        "subject": "Brett Favre",
        "question": "\"The song \"\"Sit down, you're rockin' the boat\"\" is from which musical?\"",
        "answers": [
            "Arvide Abernathy",
            "Guys And Dolls",
            "Fugue for Tinhorns",
            "Guys & Dolls",
            "Nathan Detroit",
            "Guys and Dolls",
            "Guys and Dolls (musical)",
            "Sky Masterson"
        ]
    },
    {
        "subject": "Brett Favre",
        "question": "Which part of the human body contains the most gold?",
        "answers": [
            "Fingernail bed",
            "Toe nail",
            "Periungual",
            "Fingernail Growth World Record Holders",
            "Fingernails",
            "Placoda unguis",
            "Nail trimming",
            "Toenails",
            "Nail field",
            "Fingernail ingrowing",
            "Longest nails",
            "Toenail",
            "Finger nail",
            "Long nails",
            "Hyponychial",
            "Longest fingernails",
            "Fingernail growth world record holders",
            "Periungual region",
            "HUMAN NAIL",
            "Finger nails",
            "Onychodystrophy",
            "Toe nails",
            "Unguis",
            "Fingernail",
            "Growth of nails after death",
            "Nail (anatomy)",
            "Nail anatomy"
        ]
    },
    {
        "subject": "Brett Favre",
        "question": "\"The following is the first line from which book?\"\"1801 - I have just returned from a visit to my landlord\"\".\"",
        "answers": [
            "Wutherin heights",
            "Wuthering",
            "Thrushcross Grange",
            "Wuthering Heights",
            "Wuthering heights",
            "'WUTHERING HEIGHTS'",
            "Frances Earnshaw"
        ]
    }
]